cpp/include/scheduler/scheduler.h
cpp/src/pybind_module.cpp
cpp/src/scheduler.cpp
os_simulator/__init__.py
os_simulator/os_algorithms.cpython-314-darwin.so
os_simulator/os_algorithms.pyi
os_simulator/py.typed
os_simulator-0.2.1.dist-info/licenses/LICENSE
os_simulator-0.2.1.dist-info/METADATA
os_simulator-0.2.1.dist-info/WHEEL
os_simulator-0.2.1.dist-info/top_level.txt
os_simulator-0.2.1.dist-info/RECORD
