Metadata-Version: 2.4
Name: os-simulator
Version: 0.2.1
Summary: High-performance CPU scheduling algorithms with C++ optimization
Author-email: Will Swinson <will.swinson@the10xdevelopers.com>
License-Expression: MIT
Project-URL: Homepage, https://github.com/Will-Swinson/os-simulator
Project-URL: Repository, https://github.com/Will-Swinson/os-simulator
Project-URL: BugTracker, https://github.com/Will-Swinson/os-simulator/issues
Project-URL: Documentation, https://github.com/Will-Swinson/os-simulator#readme
Classifier: Development Status :: 4 - Beta
Classifier: Intended Audience :: Education
Classifier: Intended Audience :: Developers
Classifier: Topic :: System :: Operating System
Classifier: Topic :: Software Development :: Libraries :: Python Modules
Classifier: Programming Language :: Python :: 3
Classifier: Programming Language :: Python :: 3.8
Classifier: Programming Language :: Python :: 3.9
Classifier: Programming Language :: Python :: 3.10
Classifier: Programming Language :: Python :: 3.11
Classifier: Programming Language :: Python :: 3.12
Classifier: Programming Language :: C++
Requires-Python: >=3.8
License-File: LICENSE
Requires-Dist: pybind11>=2.6.0
Dynamic: license-file
